pydna_utils/__init__.py
pydna_utils/editor.py
pydna_utils/myenzymes.py
pydna_utils/myprimers.py
pydna_utils/settings.py
pydna_utils-0.0.2.dist-info/METADATA
pydna_utils-0.0.2.dist-info/WHEEL
pydna_utils-0.0.2.dist-info/licenses/LICENSE
pydna_utils-0.0.2.dist-info/RECORD
